{"theaters": {"theaCdList": [{"cdNm": "CGV \ud53c\uce74\ub514\ub9ac 1958", "cd": "001099"}, {"cdNm": "\ud5c8\ub9ac\uc6b0\ub4dc\ud074\ub798\uc2dd", "cd": "001103"}, {"cdNm": "CGV \ub300\ud559\ub85c", "cd": "001127"}, {"cdNm": "\ub0ad\ub9cc\uadf9\uc7a5", "cd": "001227"}, {"cdNm": "\uc11c\uc6b8\uc544\ud2b8\uc2dc\ub124\ub9c8", "cd": "001062"}, {"cdNm": "\uc528\ub124\ud050\ube0c\uad11\ud654\ubb38(\uc11c\uc6b8)", "cd": "001083"}, {"cdNm": "\uc778\ub514\uc2a4\ud398\uc774\uc2a4", "cd": "001193"}, {"cdNm": "\uc11c\uc6b8\uadf9\uc7a5", "cd": "001080"}, {"cdNm": "\uc5d0\ubb34 \uc2dc\ub124\ub9c8 \uc564 \uce74\ud398", "cd": "001237"}]}, "time": "2019-11-30"}