{"theaters": {"theaCdList": [{"cdNm": "CGV \uc218\uc6d0", "cd": "002006"}, {"cdNm": "\uba54\uac00\ubc15\uc2a4 \uc218\uc6d0\ub0a8\ubb38", "cd": "002037"}, {"cdNm": "\uba54\uac00\ubc15\uc2a4 \uc218\uc6d0", "cd": "002007"}, {"cdNm": "CGV \ub3d9\uc218\uc6d0", "cd": "002116"}, {"cdNm": "\ub86f\ub370\uc2dc\ub124\ub9c8 \uc218\uc6d0 ", "cd": "002049"}, {"cdNm": "CGV \ubd81\uc218\uc6d0", "cd": "002117"}, {"cdNm": "\uba54\uac00\ubc15\uc2a4 \uc601\ud1b5", "cd": "002172"}, {"cdNm": "\ub86f\ub370\uc2dc\ub124\ub9c8 \uad11\uad50\uc544\uc6b8\ub81b", "cd": "002085"}, {"cdNm": "\ub86f\ub370\uc2dc\ub124\ub9c8\uc11c\uc218\uc6d0", "cd": "002249"}]}, "time": "2019-11-30"}